{
  "schema": "readmail-1c-v2",
  "payload_profile": "standard",
  "generated_at": "2026-06-17T13:40:14+00:00",
  "event": "return_ready",
  "case_id": 3081,
  "buyer": {
    "code": "avtoto_ru",
    "name": "АВТОТО"
  },
  "claim": {
    "kind": "shortage",
    "kind_label": "Недовоз/недопоставка",
    "number": null
  },
  "document": {
    "number": "83759",
    "date": "11.06.2026",
    "type": "УПД"
  },
  "items": [
    {
      "part_number": "GV1061R",
      "brand": "CTR",
      "product_name": "Втулка стабилизатора переднего левая",
      "quantity": 1
    },
    {
      "part_number": "NPF10",
      "brand": "NORDBERG",
      "product_name": "Разъем \"мама\" быстросъемный - елочка диам. 10 мм",
      "quantity": 2
    },
    {
      "part_number": "CQD020",
      "brand": "CAR-DEX",
      "product_name": "Патрубок радиатора отопителя",
      "quantity": 1
    }
  ],
  "comment": "недопоставка",
  "flags": {
    "has_photo": false,
    "has_document": true,
    "attachments_count": 0
  },
  "status": {
    "state": "ready_to_1c",
    "control_status": "ready_to_1c",
    "priority": "high",
    "ready_for_export": true,
    "needs_review": false
  },
  "text": {
    "subject": "КИЮ                    Недопоставка  382894  382895  382896 ",
    "body": "Добрый день! По товару была выявлена недопоставка, с информацией можете ознакомиться по ссылке ниже: При оприходовании товара по накладной 83759 от 11.06.2026 установлено, что в данной поставке отсутствует деталь GV1061R (CTR) Втулка стабилизатора переднего левая в количестве 1. Поставка №2589792 При оприходовании товара по накладной 83759 от 11.06.2026 установлено, что в данной поставке отсутствует деталь NPF10 (NORDBERG) Разъем \"мама\" быстросъемный - елочка диам. 10 мм в количестве 2. При оприходовании товара по накладной 83759 от 11.06.2026 установлено, что в данной поставке отсутствует деталь CQD020 (CAR-DEX) Патрубок радиатора отопителя в количестве 1. Поставка №2589792 В случае возникновения вопросов после поступления данной детали к Вам на склад — Вам необходимо обратиться на почту vozvrat1@avtoto.ru, в теме письма указав номер запроса на возврат. -------------------------------------------------- С уважением, Сотрудник отдела рекламаций Оператор № 959 АвтоТО | www.avtoto.ru ( http://www.avtoto.ru ) Тел.: +7(495)374-88-88, доб. № 965 E-mail: nedovoz@avtoto.ru ( http://e.mail.ru/compose/?mailto=mailto%3anedovoz@avtoto.ru ) --"
  },
  "attachments": [],
  "source": {
    "raw_email_id": 3805,
    "message_id": "<1781516699.547469529@f338.i.mail.ru>",
    "received_at": "2026-06-15T09:44:59+00:00"
  }
}